postal_regex/__init__.py
postal_regex/validator.py
postal_regex/data/postal_codes.json
postal_regex/data/schema.json
postal_regex-1.0.0.dist-info/licenses/LICENSE
postal_regex-1.0.0.dist-info/METADATA
postal_regex-1.0.0.dist-info/WHEEL
postal_regex-1.0.0.dist-info/top_level.txt
postal_regex-1.0.0.dist-info/RECORD
