Metadata-Version: 2.4
Name: postal_regex
Version: 1.0.0
Summary: Postal code regex validator
Author-email: Ankit Gadling <ankitgadling2@gmail.com>
License: MIT
Requires-Python: >=3.10
License-File: LICENSE
Dynamic: license-file
